django_telethon/__init__.py
django_telethon/admin.py
django_telethon/apps.py
django_telethon/callback.py
django_telethon/default_settings.py
django_telethon/importer.py
django_telethon/rabbitmq.py
django_telethon/receivers.py
django_telethon/sessions.py
django_telethon/signals.py
django_telethon/urls.py
django_telethon/utils.py
django_telethon/views.py
django_telethon/management/__init__.py
django_telethon/management/commands/__init__.py
django_telethon/management/commands/runtelegram.py
django_telethon/migrations/0001_initial.py
django_telethon/migrations/0002_updatestate_entity.py
django_telethon/migrations/0003_alter_updatestate_entity_id.py
django_telethon/migrations/__init__.py
django_telethon/models/__init__.py
django_telethon/models/apps.py
django_telethon/models/entities.py
django_telethon/models/login.py
django_telethon/models/sentfiles.py
django_telethon/models/sessions.py
django_telethon/models/states.py
django_telethon-1.4.0.dist-info/LICENSE
django_telethon-1.4.0.dist-info/METADATA
django_telethon-1.4.0.dist-info/WHEEL
django_telethon-1.4.0.dist-info/top_level.txt
django_telethon-1.4.0.dist-info/RECORD
